pwerpy/__init__.py
pwerpy/powerpy.py
pwerpy/skills.py
pwerpy-1.0.1.dist-info/LICENSE
pwerpy-1.0.1.dist-info/METADATA
pwerpy-1.0.1.dist-info/WHEEL
pwerpy-1.0.1.dist-info/top_level.txt
pwerpy-1.0.1.dist-info/RECORD
