Metadata-Version: 2.1
Name: pwerpy
Version: 1.0.1
Summary: Easier communication between Microsoft Power BI REST API and a client
Home-page: https://github.com/4ssef/powerpy_package
Author: 4ssef (Fernando Assef)
Author-email: fernandoassef@hotmail.com
Keywords: python,power bi,power bi rest api,powerbi
Classifier: Development Status :: 5 - Production/Stable
Classifier: Intended Audience :: Developers
Classifier: Programming Language :: Python :: 3.9
Classifier: Operating System :: OS Independent
Classifier: Intended Audience :: Information Technology
Classifier: License :: OSI Approved :: MIT License
Classifier: Natural Language :: English
Classifier: Topic :: Software Development :: Libraries :: Python Modules
Requires-Python: <4,>=3.7
License-File: LICENSE
Requires-Dist: requests
Requires-Dist: msal
